<?xml version="1.0" encoding="UTF-8"?>

<process-definition
  xmlns=""  name="devil.NightLabs.org:Invoice.Vendor">
   <start-state name="devil.NightLabs.org:created">
      <transition name="" to="aborted"></transition>
      <transition name="finalize" to="devil.NightLabs.org:finalized"></transition>
   </start-state>
   <state name="devil.NightLabs.org:finalized">
      <transition name="tr3" to="devil.NightLabs.org:doubtful"></transition>
      <transition name="pay" to="isBooked"></transition>
      <transition name="book" to="booked.1"></transition>
   </state>
   <end-state name="aborted"></end-state>
   <state name="devil.NightLabs.org:doubtful">
      <transition name="" to="devil.NightLabs.org:uncollectable"></transition>
      <transition name="pay" to="isBooked"></transition>
   </state>
   <end-state name="devil.NightLabs.org:uncollectable"></end-state>
   <end-state name="devil.NightLabs.org:paid"></end-state>
   <decision name="isBooked">
      <transition name="notYetBooked" to="waitForBooking"></transition>
      <transition name="alreadyBooked" to="devil.NightLabs.org:paid"></transition>
   </decision>
   <state name="waitForBooking">
      <transition name="" to="booked.2"></transition>
   </state>
   <node name="booked.1">
      <transition name="" to="devil.NightLabs.org:finalized"></transition>
   </node>
   <node name="booked.2">
      <transition name="" to="devil.NightLabs.org:paid"></transition>
   </node>
</process-definition>